{
    "$schema": "http://json-schema.org/draft-07/schema#",
    "$id": "https://variate.ca/definitions/traffic.json",
    "type": "object",
    "meta:status": "stable",
    "meta:license": "MIT",
    "title": "Traffic",
    "description": "The traffic object contains a minimum and maximum percentage of traffic.",
    "required": [
        "max",
        "min"
    ],
    "properties": {
        "max": {
            "$ref": "https://variate.ca/definitions/percentage.json",
            "title": "Minimum traffic percentage allowed."
        },
        "min": {
            "$ref": "https://variate.ca/definitions/percentage.json",
            "title": "Maximum traffic percentage allowed."
        }
    },
    "additionalProperties": false
}