{
    "$schema": "http://json-schema.org/draft-07/schema#",
    "$id": "https://variate.ca/definitions/bucket.json",
    "meta:status": "stable",
    "meta:license": "MIT",
    "type": "object",
    "title": "Bucket",
    "description": "Special bucket of traffic for canary experiment (experiment ran on a reduced percentage of traffic regardless of targeting.",
    "required": [
        "min",
        "max",
        "experiments"
    ],
    "properties": {
        "min": {
            "$ref": "https://variate.ca/definitions/percentage.json"
        },
        "max": {
            "$ref": "https://variate.ca/definitions/percentage.json"
        },
        "experiments": {
            "type": "array",
            "title": "Experiments",
            "items": {
                "$ref": "https://variate.ca/definitions/experiment.json"
            }
        }
    },
    "additionalProperties": false
}
